canvas_fonts/__init__.py
canvas_fonts/data.py
canvas_fonts/font_list.py
canvas_fonts/fonts/ABeeZee.ttf
canvas_fonts/fonts/Abel.ttf
canvas_fonts/fonts/Abhaya.ttf
canvas_fonts/fonts/Abril.ttf
canvas_fonts/fonts/Adamina.ttf
canvas_fonts/fonts/Advent.ttf
canvas_fonts/fonts/Aguafina.ttf
canvas_fonts/fonts/Akaya.ttf
canvas_fonts/fonts/Akronim.ttf
canvas_fonts/fonts/Aladin.ttf
canvas_fonts/fonts/Alata.ttf
canvas_fonts/fonts/Alatsi.ttf
canvas_fonts/fonts/Aldrich.ttf
canvas_fonts/fonts/Alef.ttf
canvas_fonts/fonts/Alegreya.ttf
canvas_fonts/fonts/Alice.ttf
canvas_fonts/fonts/Alike.ttf
canvas_fonts/fonts/Alkalami.ttf
canvas_fonts/fonts/Allan.ttf
canvas_fonts/fonts/Allerta.ttf
canvas_fonts/fonts/Allura.ttf
canvas_fonts/fonts/Almarai.ttf
canvas_fonts/fonts/Almendra.ttf
canvas_fonts/fonts/Amarante.ttf
canvas_fonts/fonts/Amaranth.ttf
canvas_fonts/fonts/Amatic.ttf
canvas_fonts/fonts/Amethysta.ttf
canvas_fonts/fonts/Andada.ttf
canvas_fonts/fonts/Andika.ttf
canvas_fonts/fonts/Angkor.ttf
canvas_fonts/fonts/AnonymousPro.ttf
canvas_fonts/fonts/Antic.ttf
canvas_fonts/fonts/Anton.ttf
canvas_fonts/fonts/Arapey.ttf
canvas_fonts/fonts/Arbutus.ttf
canvas_fonts/fonts/Architects.ttf
canvas_fonts/fonts/Archivo.ttf
canvas_fonts/fonts/Arima.ttf
canvas_fonts/fonts/Arimo.ttf
canvas_fonts/fonts/Artifika.ttf
canvas_fonts/fonts/Arvo.ttf
canvas_fonts/fonts/Asap.ttf
canvas_fonts/fonts/Asset.ttf
canvas_fonts/fonts/Assistant.ttf
canvas_fonts/fonts/Astloch.ttf
canvas_fonts/fonts/Asul.ttf
canvas_fonts/fonts/Athiti.ttf
canvas_fonts/fonts/Atma.ttf
canvas_fonts/fonts/Atomic.ttf
canvas_fonts/fonts/Aubrey.ttf
canvas_fonts/fonts/Audiowide.ttf
canvas_fonts/fonts/Autour.ttf
canvas_fonts/fonts/Average.ttf
canvas_fonts/fonts/Averia.ttf
canvas_fonts/fonts/BPmono.ttf
canvas_fonts/fonts/BadScript.ttf
canvas_fonts/fonts/Bahiana.ttf
canvas_fonts/fonts/Baloo.ttf
canvas_fonts/fonts/Bangers.ttf
canvas_fonts/fonts/Barlow.ttf
canvas_fonts/fonts/BebasNeue.ttf
canvas_fonts/fonts/Bellota.ttf
canvas_fonts/fonts/BenchNine.ttf
canvas_fonts-0.2.0.dist-info/METADATA
canvas_fonts-0.2.0.dist-info/WHEEL
canvas_fonts-0.2.0.dist-info/licenses/LICENSE
canvas_fonts-0.2.0.dist-info/RECORD
