Metadata-Version: 2.4
Name: canvas-fonts
Version: 0.2.0
Summary: A library providing 200+ fonts for canvas editors
Project-URL: Homepage, https://github.com/aipresso/canvas_fonts
Project-URL: Bug Tracker, https://github.com/aipresso/canvas_fonts/issues
Author-email: Sumedh Patil <sumedh@aipresso.com>
License: MIT License
License-File: LICENSE
Classifier: License :: OSI Approved :: MIT License
Classifier: Operating System :: OS Independent
Classifier: Programming Language :: Python :: 3
Requires-Python: >=3.8
